SmiToText/SmiToText.py
SmiToText/__init__.py
SmiToText/find/__init__.py
SmiToText/find/extract_kakao_noun.py
SmiToText/find/extract_konlply_noun.py
SmiToText/find/extract_mecab_multi_noun.py
SmiToText/find/extract_mecab_multi_noun_advance.py
SmiToText/find/extract_mecab_nng.py
SmiToText/find/extract_mecab_noun.py
SmiToText/font/Goyang.ttf
SmiToText/font/NanumBarunGothic.ttf
SmiToText/font/NanumGothic_Coding.ttf
SmiToText/font/__init__.py
SmiToText/frequency/__init__.py
SmiToText/frequency/word.py
SmiToText/mecab/__init__.py
SmiToText/mecab/mecabDictGenerate.py
SmiToText/mecab/mecabdict_file_gen.py
SmiToText/spacing/__init__.py
SmiToText/spacing/koCrfSpacing.py
SmiToText/spacing/koPyCrfsuitSpacing.py
SmiToText/spacing/koPyCrfsuitSpacingUtil.py
SmiToText/spacing/koSoySpacing.py
SmiToText/spacing/mecabSpacing.py
SmiToText/spacing/spacingInterface.py
SmiToText/spacing/spacingTrain.py
SmiToText/spacing/spacingUtil.py
SmiToText/tokenizer/__init__.py
SmiToText/tokenizer/mecab.py
SmiToText/tokenizer/nltk.py
SmiToText/util/__init__.py
SmiToText/util/util.py
SmiToText/wordcheck/__init__.py
SmiToText/wordcheck/koLastCharCheck.py
SmiToText/wordcheck/koNounExtract.py
SmiToText/wordcloud/__init__.py
SmiToText/wordcloud/cloudimage.py
SmiToText-0.1665.dist-info/METADATA
SmiToText-0.1665.dist-info/WHEEL
SmiToText-0.1665.dist-info/top_level.txt
SmiToText-0.1665.dist-info/RECORD
