Metadata-Version: 2.1
Name: SmiToText
Version: 0.1665
Summary: test processing
Home-page: https://github.com/jjeaby/SmiToText
Author: Lee Yong Jin
Author-email: jjeaby@gmail.com
License: Apache 2.0
Platform: UNKNOWN
Classifier: Programming Language :: Python :: 3
Classifier: Programming Language :: Python :: 3.2
Classifier: Programming Language :: Python :: 3.3
Classifier: Programming Language :: Python :: 3.4
Classifier: Programming Language :: Python :: 3.5
Classifier: Programming Language :: Python :: 3.6
Classifier: Programming Language :: Python :: 3.7
Requires-Dist: numpy
Requires-Dist: mecab-python3
Requires-Dist: nltk
Requires-Dist: spacy
Requires-Dist: langdetect
Requires-Dist: soyspacing
Requires-Dist: scipy
Requires-Dist: scikit-learn
Requires-Dist: python-crfsuite
Requires-Dist: tensorflow
Requires-Dist: caret
Requires-Dist: krwordrank
Requires-Dist: wordcloud
Requires-Dist: matplotlib
Requires-Dist: pillow
Requires-Dist: konlpy
